[
  {
    "trend_arrow": "45_UP", 
    "display_time": "2017-01-02T09:04:54-08:00", 
    "noise": 1, 
    "system_time": "2017-01-02T17:04:15-08:00", 
    "direction": "FortyFiveUp", 
    "sgv": 150, 
    "dateString": "2017-01-02T09:04:54-08:00", 
    "date": 1483376694000, 
    "unfiltered": 171360, 
    "filtered": 162336, 
    "device": "openaps://indy-e1/cgm", 
    "rssi": 192, 
    "type": "sgv", 
    "glucose": 150
  }, 
  {
    "trend_arrow": "45_UP", 
    "display_time": "2017-01-02T08:59:54-08:00", 
    "noise": 1, 
    "system_time": "2017-01-02T16:59:15-08:00", 
    "direction": "FortyFiveUp", 
    "sgv": 142, 
    "dateString": "2017-01-02T08:59:54-08:00", 
    "date": 1483376394000, 
    "unfiltered": 163936, 
    "filtered": 155840, 
    "device": "openaps://indy-e1/cgm", 
    "rssi": 187, 
    "type": "sgv", 
    "glucose": 142
  }
]