[
  {
    "trend_arrow": "FLAT", 
    "display_time": "2016-12-20T00:34:21-08:00", 
    "noise": 1, 
    "system_time": "2016-12-20T08:20:50-08:00", 
    "direction": "Flat", 
    "sgv": 114, 
    "dateString": "2016-12-20T00:34:21-08:00", 
    "date": 1482222861000, 
    "unfiltered": 128016, 
    "filtered": 126800, 
    "device": "openaps://indy-e1/cgm", 
    "rssi": 194, 
    "type": "sgv", 
    "glucose": 114
  }, 
  {
    "trend_arrow": "45_UP", 
    "display_time": "2016-12-20T00:29:21-08:00", 
    "noise": 1, 
    "system_time": "2016-12-20T08:15:50-08:00", 
    "direction": "FortyFiveUp", 
    "sgv": 116, 
    "dateString": "2016-12-20T00:29:21-08:00", 
    "date": 1482222561000, 
    "unfiltered": 129728, 
    "filtered": 122288, 
    "device": "openaps://indy-e1/cgm", 
    "rssi": 195, 
    "type": "sgv", 
    "glucose": 116
  }
]