[
  {
    "trend_arrow": "FLAT", 
    "display_time": "2017-01-07T05:58:35-08:00", 
    "noise": 1, 
    "system_time": "2017-01-07T13:44:36-08:00", 
    "direction": "Flat", 
    "sgv": 101, 
    "dateString": "2017-01-07T05:58:35-08:00", 
    "date": 1483797515000, 
    "unfiltered": 106240, 
    "filtered": 106912, 
    "device": "openaps://indy-e1/cgm", 
    "rssi": 201, 
    "type": "sgv", 
    "glucose": 101
  }, 
  {
    "trend_arrow": "FLAT", 
    "display_time": "2017-01-07T05:53:35-08:00", 
    "noise": 1, 
    "system_time": "2017-01-07T13:39:36-08:00", 
    "direction": "Flat", 
    "sgv": 98, 
    "dateString": "2017-01-07T05:53:35-08:00", 
    "date": 1483797215000, 
    "unfiltered": 103264, 
    "filtered": 107440, 
    "device": "openaps://indy-e1/cgm", 
    "rssi": 198, 
    "type": "sgv", 
    "glucose": 98
  }
]