[
  {
    "trend_arrow": "NOT_COMPUTABLE", 
    "display_time": "2016-12-21T00:19:17-08:00", 
    "noise": 3, 
    "system_time": "2016-12-21T08:05:46-08:00", 
    "direction": "NOT COMPUTABLE", 
    "sgv": 127, 
    "dateString": "2016-12-21T00:19:17-08:00", 
    "date": 1482308357000, 
    "unfiltered": 145760, 
    "filtered": 140032, 
    "device": "openaps://indy-e1/cgm", 
    "rssi": 198, 
    "type": "sgv", 
    "glucose": 127
  }, 
  {
    "trend_arrow": "NOT_COMPUTABLE", 
    "display_time": "2016-12-21T00:14:17-08:00", 
    "noise": 3, 
    "system_time": "2016-12-21T08:00:46-08:00", 
    "direction": "NOT COMPUTABLE", 
    "sgv": 121, 
    "dateString": "2016-12-21T00:14:17-08:00", 
    "date": 1482308057000, 
    "unfiltered": 142976, 
    "filtered": 134368, 
    "device": "openaps://indy-e1/cgm", 
    "rssi": 197, 
    "type": "sgv", 
    "glucose": 121
  }
]