[
  {
    "trend_arrow": "SINGLE_DOWN", 
    "display_time": "2017-01-01T22:54:56-08:00", 
    "noise": 1, 
    "system_time": "2017-01-02T06:54:16-08:00", 
    "direction": "SingleDown", 
    "sgv": 117, 
    "dateString": "2017-01-01T22:54:56-08:00", 
    "date": 1483340096000, 
    "unfiltered": 131584, 
    "filtered": 148128, 
    "device": "openaps://indy-e1/cgm", 
    "rssi": 182, 
    "type": "sgv", 
    "glucose": 117
  }, 
  {
    "trend_arrow": "SINGLE_DOWN", 
    "display_time": "2017-01-01T22:49:56-08:00", 
    "noise": 1, 
    "system_time": "2017-01-02T06:49:16-08:00", 
    "direction": "SingleDown", 
    "sgv": 127, 
    "dateString": "2017-01-01T22:49:56-08:00", 
    "date": 1483339796000, 
    "unfiltered": 140160, 
    "filtered": 159872, 
    "device": "openaps://indy-e1/cgm", 
    "rssi": 181, 
    "type": "sgv", 
    "glucose": 127
  }
]