[
  {
    "trend_arrow": "FLAT", 
    "display_time": "2017-01-04T09:59:48-08:00", 
    "noise": 1, 
    "system_time": "2017-01-04T17:59:09-08:00", 
    "direction": "Flat", 
    "sgv": 84, 
    "dateString": "2017-01-04T09:59:48-08:00", 
    "date": 1483552788000, 
    "unfiltered": 96272, 
    "filtered": 97456, 
    "device": "openaps://indy-e1/cgm", 
    "rssi": 192, 
    "type": "sgv", 
    "glucose": 84
  }, 
  {
    "trend_arrow": "FLAT", 
    "display_time": "2017-01-04T09:54:48-08:00", 
    "noise": 1, 
    "system_time": "2017-01-04T17:54:08-08:00", 
    "direction": "Flat", 
    "sgv": 84, 
    "dateString": "2017-01-04T09:54:48-08:00", 
    "date": 1483552488000, 
    "unfiltered": 96400, 
    "filtered": 97808, 
    "device": "openaps://indy-e1/cgm", 
    "rssi": 175, 
    "type": "sgv", 
    "glucose": 84
  }
]