[
  {
    "trend_arrow": "FLAT", 
    "display_time": "2016-12-20T03:14:21-08:00", 
    "noise": 1, 
    "system_time": "2016-12-20T11:00:50-08:00", 
    "direction": "Flat", 
    "sgv": 160, 
    "dateString": "2016-12-20T03:14:21-08:00", 
    "date": 1482232461000, 
    "unfiltered": 168320, 
    "filtered": 161600, 
    "device": "openaps://indy-e1/cgm", 
    "rssi": 186, 
    "type": "sgv", 
    "glucose": 160
  }, 
  {
    "trend_arrow": "FLAT", 
    "display_time": "2016-12-20T03:09:20-08:00", 
    "noise": 1, 
    "system_time": "2016-12-20T10:55:50-08:00", 
    "direction": "Flat", 
    "sgv": 154, 
    "dateString": "2016-12-20T03:09:20-08:00", 
    "date": 1482232160000, 
    "unfiltered": 163648, 
    "filtered": 158080, 
    "device": "openaps://indy-e1/cgm", 
    "rssi": 186, 
    "type": "sgv", 
    "glucose": 154
  }
]