[
  {
    "trend_arrow": "45_DOWN", 
    "display_time": "2017-01-02T21:59:53-08:00", 
    "noise": 1, 
    "system_time": "2017-01-03T05:59:13-08:00", 
    "direction": "FortyFiveDown", 
    "sgv": 72, 
    "dateString": "2017-01-02T21:59:53-08:00", 
    "date": 1483423193000, 
    "unfiltered": 98208, 
    "filtered": 108960, 
    "device": "openaps://indy-e1/cgm", 
    "rssi": 178, 
    "type": "sgv", 
    "glucose": 72
  }, 
  {
    "trend_arrow": "FLAT", 
    "display_time": "2017-01-02T21:54:53-08:00", 
    "noise": 1, 
    "system_time": "2017-01-03T05:54:13-08:00", 
    "direction": "Flat", 
    "sgv": 80, 
    "dateString": "2017-01-02T21:54:53-08:00", 
    "date": 1483422893000, 
    "unfiltered": 105520, 
    "filtered": 113120, 
    "device": "openaps://indy-e1/cgm", 
    "rssi": 169, 
    "type": "sgv", 
    "glucose": 80
  }
]