[
  {
    "trend_arrow": "FLAT", 
    "display_time": "2017-01-02T21:24:53-08:00", 
    "noise": 1, 
    "system_time": "2017-01-03T05:24:13-08:00", 
    "direction": "Flat", 
    "sgv": 77, 
    "dateString": "2017-01-02T21:24:53-08:00", 
    "date": 1483421093000, 
    "unfiltered": 102896, 
    "filtered": 102560, 
    "device": "openaps://indy-e1/cgm", 
    "rssi": 189, 
    "type": "sgv", 
    "glucose": 77
  }, 
  {
    "trend_arrow": "45_DOWN", 
    "display_time": "2017-01-02T21:19:53-08:00", 
    "noise": 1, 
    "system_time": "2017-01-03T05:19:13-08:00", 
    "direction": "FortyFiveDown", 
    "sgv": 75, 
    "dateString": "2017-01-02T21:19:53-08:00", 
    "date": 1483420793000, 
    "unfiltered": 101040, 
    "filtered": 109184, 
    "device": "openaps://indy-e1/cgm", 
    "rssi": 176, 
    "type": "sgv", 
    "glucose": 75
  }
]