[
  {
    "trend_arrow": "FLAT", 
    "display_time": "2016-12-27T22:40:04-08:00", 
    "noise": 1, 
    "system_time": "2016-12-28T06:26:24-08:00", 
    "direction": "Flat", 
    "sgv": 108, 
    "dateString": "2016-12-27T22:40:04-08:00", 
    "date": 1482907204000, 
    "unfiltered": 121344, 
    "filtered": 119664, 
    "device": "openaps://indy-e1/cgm", 
    "rssi": 187, 
    "type": "sgv", 
    "glucose": 108
  }, 
  {
    "trend_arrow": "FLAT", 
    "display_time": "2016-12-27T22:35:04-08:00", 
    "noise": 1, 
    "system_time": "2016-12-28T06:21:24-08:00", 
    "direction": "Flat", 
    "sgv": 103, 
    "dateString": "2016-12-27T22:35:04-08:00", 
    "date": 1482906904000, 
    "unfiltered": 117152, 
    "filtered": 121328, 
    "device": "openaps://indy-e1/cgm", 
    "rssi": 186, 
    "type": "sgv", 
    "glucose": 103
  }
]