[
  {
    "trend_arrow": "45_UP", 
    "display_time": "2016-12-28T17:10:01-08:00", 
    "noise": 1, 
    "system_time": "2016-12-29T00:56:21-08:00", 
    "direction": "FortyFiveUp", 
    "sgv": 154, 
    "dateString": "2016-12-28T17:10:01-08:00", 
    "date": 1482973801000, 
    "unfiltered": 159744, 
    "filtered": 149408, 
    "device": "openaps://indy-e1/cgm", 
    "rssi": 173, 
    "type": "sgv", 
    "glucose": 154
  }, 
  {
    "trend_arrow": "45_UP", 
    "display_time": "2016-12-28T17:05:01-08:00", 
    "noise": 1, 
    "system_time": "2016-12-29T00:51:21-08:00", 
    "direction": "FortyFiveUp", 
    "sgv": 148, 
    "dateString": "2016-12-28T17:05:01-08:00", 
    "date": 1482973501000, 
    "unfiltered": 154848, 
    "filtered": 142272, 
    "device": "openaps://indy-e1/cgm", 
    "rssi": 185, 
    "type": "sgv", 
    "glucose": 148
  }
]