[
  {
    "trend_arrow": "FLAT", 
    "display_time": "2016-12-16T21:19:23-08:00", 
    "noise": 1, 
    "system_time": "2016-12-17T04:11:47-08:00", 
    "direction": "Flat", 
    "sgv": 201, 
    "dateString": "2016-12-16T21:19:23-08:00", 
    "date": 1481951963000, 
    "unfiltered": 230144, 
    "filtered": 226688, 
    "device": "openaps://indy-e1/cgm", 
    "rssi": 428, 
    "type": "sgv", 
    "glucose": 201
  }, 
  {
    "trend_arrow": "FLAT", 
    "display_time": "2016-12-16T21:14:23-08:00", 
    "noise": 1, 
    "system_time": "2016-12-17T04:06:46-08:00", 
    "direction": "Flat", 
    "sgv": 199, 
    "dateString": "2016-12-16T21:14:23-08:00", 
    "date": 1481951663000, 
    "unfiltered": 227488, 
    "filtered": 225664, 
    "device": "openaps://indy-e1/cgm", 
    "rssi": 192, 
    "type": "sgv", 
    "glucose": 199
  }
]