[
  {
    "trend_arrow": "FLAT", 
    "display_time": "2016-12-20T05:29:20-08:00", 
    "noise": 1, 
    "system_time": "2016-12-20T13:15:50-08:00", 
    "direction": "Flat", 
    "sgv": 156, 
    "dateString": "2016-12-20T05:29:20-08:00", 
    "date": 1482240560000, 
    "unfiltered": 165152, 
    "filtered": 160384, 
    "device": "openaps://indy-e1/cgm", 
    "rssi": 183, 
    "type": "sgv", 
    "glucose": 156
  }, 
  {
    "trend_arrow": "FLAT", 
    "display_time": "2016-12-20T05:24:21-08:00", 
    "noise": 1, 
    "system_time": "2016-12-20T13:10:50-08:00", 
    "direction": "Flat", 
    "sgv": 152, 
    "dateString": "2016-12-20T05:24:21-08:00", 
    "date": 1482240261000, 
    "unfiltered": 161664, 
    "filtered": 158112, 
    "device": "openaps://indy-e1/cgm", 
    "rssi": 450, 
    "type": "sgv", 
    "glucose": 152
  }
]