[
  {
    "trend_arrow": "FLAT", 
    "display_time": "2017-01-03T13:24:51-08:00", 
    "noise": 1, 
    "system_time": "2017-01-03T21:24:11-08:00", 
    "direction": "Flat", 
    "sgv": 127, 
    "dateString": "2017-01-03T13:24:51-08:00", 
    "device": "openaps://indy-e1/cgm", 
    "unfiltered": 133952, 
    "rssi": 196, 
    "date": 1483478691000, 
    "filtered": 131648, 
    "type": "sgv", 
    "glucose": 127
  }, 
  {
    "trend_arrow": "FLAT", 
    "display_time": "2017-01-03T13:19:51-08:00", 
    "noise": 1, 
    "system_time": "2017-01-03T21:19:11-08:00", 
    "direction": "Flat", 
    "sgv": 124, 
    "dateString": "2017-01-03T13:19:51-08:00", 
    "device": "openaps://indy-e1/cgm", 
    "unfiltered": 132064, 
    "rssi": 217, 
    "date": 1483478391000, 
    "filtered": 134944, 
    "type": "sgv", 
    "glucose": 124
  }
]