[
  {
    "trend_arrow": "FLAT", 
    "display_time": "2016-12-20T13:04:19-08:00", 
    "noise": 1, 
    "system_time": "2016-12-20T20:50:48-08:00", 
    "direction": "Flat", 
    "sgv": 150, 
    "dateString": "2016-12-20T13:04:19-08:00", 
    "device": "openaps://indy-e1/cgm", 
    "unfiltered": 160032, 
    "rssi": 167, 
    "date": 1482267859000, 
    "filtered": 157536, 
    "type": "sgv", 
    "glucose": 150
  }, 
  {
    "trend_arrow": "45_UP", 
    "display_time": "2016-12-20T12:59:19-08:00", 
    "noise": 1, 
    "system_time": "2016-12-20T20:45:49-08:00", 
    "direction": "FortyFiveUp", 
    "sgv": 149, 
    "dateString": "2016-12-20T12:59:19-08:00", 
    "device": "openaps://indy-e1/cgm", 
    "unfiltered": 159296, 
    "rssi": 421, 
    "date": 1482267559000, 
    "filtered": 152096, 
    "type": "sgv", 
    "glucose": 149
  }
]