[
  {
    "trend_arrow": "FLAT", 
    "display_time": "2016-12-31T08:45:00-08:00", 
    "noise": 1, 
    "system_time": "2016-12-31T16:44:21-08:00", 
    "direction": "Flat", 
    "sgv": 96, 
    "dateString": "2016-12-31T08:45:00-08:00", 
    "device": "openaps://indy-e1/cgm", 
    "unfiltered": 127856, 
    "rssi": 168, 
    "date": 1483202700000, 
    "filtered": 130640, 
    "type": "sgv", 
    "glucose": 96
  }, 
  {
    "trend_arrow": "FLAT", 
    "display_time": "2016-12-31T08:40:00-08:00", 
    "noise": 1, 
    "system_time": "2016-12-31T16:39:21-08:00", 
    "direction": "Flat", 
    "sgv": 97, 
    "dateString": "2016-12-31T08:40:00-08:00", 
    "device": "openaps://indy-e1/cgm", 
    "unfiltered": 128400, 
    "rssi": 166, 
    "date": 1483202400000, 
    "filtered": 133088, 
    "type": "sgv", 
    "glucose": 97
  }
]