[
  {
    "trend_arrow": "45_DOWN", 
    "system_time": "2017-01-01T23:09:17", 
    "noise": 1, 
    "direction": "FortyFiveDown", 
    "sgv": 58, 
    "display_time": "2017-01-01T15:09:56", 
    "date": 1483312196000.0, 
    "dateString": "2017-01-01T15:09:56", 
    "unfiltered": 99840, 
    "filtered": 106880, 
    "device": "openaps://indy-e1/cgm", 
    "rssi": 180, 
    "type": "sgv", 
    "glucose": 58
  }, 
  {
    "trend_arrow": "NOT_COMPUTABLE", 
    "system_time": "2017-01-01T23:04:17", 
    "noise": 1, 
    "direction": "NOT COMPUTABLE", 
    "sgv": 61, 
    "display_time": "2017-01-01T15:04:56", 
    "date": 1483311896000.0, 
    "dateString": "2017-01-01T15:04:56", 
    "unfiltered": 103280, 
    "filtered": 113520, 
    "device": "openaps://indy-e1/cgm", 
    "rssi": 178, 
    "type": "sgv", 
    "glucose": 61
  }, 
  {
    "trend_arrow": "NOT_COMPUTABLE", 
    "system_time": "2017-01-01T22:59:17", 
    "noise": 1, 
    "direction": "NOT COMPUTABLE", 
    "sgv": 66, 
    "display_time": "2017-01-01T14:59:56", 
    "date": 1483311596000.0, 
    "dateString": "2017-01-01T14:59:56", 
    "unfiltered": 108304, 
    "filtered": 119792, 
    "device": "openaps://indy-e1/cgm", 
    "rssi": 181, 
    "type": "sgv", 
    "glucose": 66
  }, 
  {
    "trend_arrow": "NOT_COMPUTABLE", 
    "system_time": "2017-01-01T22:54:17", 
    "noise": 1, 
    "direction": "NOT COMPUTABLE", 
    "sgv": 74, 
    "display_time": "2017-01-01T14:54:56", 
    "date": 1483311296000.0, 
    "dateString": "2017-01-01T14:54:56", 
    "unfiltered": 116384, 
    "filtered": 124608, 
    "device": "openaps://indy-e1/cgm", 
    "rssi": 178, 
    "type": "sgv", 
    "glucose": 74
  }, 
  {
    "trend_arrow": "NOT_COMPUTABLE", 
    "system_time": "2017-01-01T22:49:17", 
    "noise": 1, 
    "direction": "NOT COMPUTABLE", 
    "sgv": 81, 
    "display_time": "2017-01-01T14:49:56", 
    "date": 1483310996000.0, 
    "dateString": "2017-01-01T14:49:56", 
    "unfiltered": 122640, 
    "filtered": 128096, 
    "device": "openaps://indy-e1/cgm", 
    "rssi": 187, 
    "type": "sgv", 
    "glucose": 81
  }
]