[
  {
    "trend_arrow": "FLAT", 
    "display_time": "2016-12-29T12:39:57-08:00", 
    "noise": 1, 
    "system_time": "2016-12-29T20:26:18-08:00", 
    "direction": "Flat", 
    "sgv": 91, 
    "dateString": "2016-12-29T12:39:57-08:00", 
    "device": "openaps://indy-e1/cgm", 
    "unfiltered": 108080, 
    "rssi": 195, 
    "date": 1483043997000, 
    "filtered": 99760, 
    "type": "sgv", 
    "glucose": 91
  }, 
  {
    "trend_arrow": "FLAT", 
    "display_time": "2016-12-29T12:34:58-08:00", 
    "noise": 1, 
    "system_time": "2016-12-29T20:21:18-08:00", 
    "direction": "Flat", 
    "sgv": 83, 
    "dateString": "2016-12-29T12:34:58-08:00", 
    "device": "openaps://indy-e1/cgm", 
    "unfiltered": 101216, 
    "rssi": 450, 
    "date": 1483043698000, 
    "filtered": 98032, 
    "type": "sgv", 
    "glucose": 83
  }
]