[
  {
    "trend_arrow": "FLAT", 
    "display_time": "2016-12-28T10:45:02-08:00", 
    "noise": 1, 
    "system_time": "2016-12-28T18:31:22-08:00", 
    "direction": "Flat", 
    "sgv": 138, 
    "dateString": "2016-12-28T10:45:02-08:00", 
    "device": "openaps://indy-e1/cgm", 
    "unfiltered": 146592, 
    "rssi": 176, 
    "date": 1482950702000, 
    "filtered": 148832, 
    "type": "sgv", 
    "glucose": 138
  }, 
  {
    "trend_arrow": "FLAT", 
    "display_time": "2016-12-28T10:40:02-08:00", 
    "noise": 1, 
    "system_time": "2016-12-28T18:26:22-08:00", 
    "direction": "Flat", 
    "sgv": 141, 
    "dateString": "2016-12-28T10:40:02-08:00", 
    "device": "openaps://indy-e1/cgm", 
    "unfiltered": 149152, 
    "rssi": 162, 
    "date": 1482950402000, 
    "filtered": 147712, 
    "type": "sgv", 
    "glucose": 141
  }
]