[
  {
    "trend_arrow": "NOT_COMPUTABLE", 
    "display_time": "2017-01-01T08:24:58-08:00", 
    "noise": 1, 
    "system_time": "2017-01-01T16:24:18-08:00", 
    "direction": "NOT COMPUTABLE", 
    "sgv": 96, 
    "dateString": "2017-01-01T08:24:58-08:00", 
    "device": "openaps://indy-e1/cgm", 
    "unfiltered": 137920, 
    "rssi": 424, 
    "date": 1483287898000, 
    "filtered": 144256, 
    "type": "sgv", 
    "glucose": 96
  }, 
  {
    "trend_arrow": "NOT_COMPUTABLE", 
    "display_time": "2017-01-01T08:19:57-08:00", 
    "noise": 1, 
    "system_time": "2017-01-01T16:19:18-08:00", 
    "direction": "NOT COMPUTABLE", 
    "sgv": 99, 
    "dateString": "2017-01-01T08:19:57-08:00", 
    "device": "openaps://indy-e1/cgm", 
    "unfiltered": 141600, 
    "rssi": 160, 
    "date": 1483287597000, 
    "filtered": 147936, 
    "type": "sgv", 
    "glucose": 99
  }
]