[
  {
    "trend_arrow": "FLAT", 
    "system_time": "2017-01-07T14:09:36", 
    "noise": 1, 
    "direction": "Flat", 
    "sgv": 107, 
    "display_time": "2017-01-07T06:23:35", 
    "date": 1483799015000.0, 
    "dateString": "2017-01-07T06:23:35", 
    "unfiltered": 111216, 
    "filtered": 112160, 
    "device": "openaps://indy-e1/cgm", 
    "rssi": 193, 
    "type": "sgv", 
    "glucose": 107
  }, 
  {
    "trend_arrow": "FLAT", 
    "system_time": "2017-01-07T14:04:36", 
    "noise": 1, 
    "direction": "Flat", 
    "sgv": 107, 
    "display_time": "2017-01-07T06:18:35", 
    "date": 1483798715000.0, 
    "dateString": "2017-01-07T06:18:35", 
    "unfiltered": 111136, 
    "filtered": 111024, 
    "device": "openaps://indy-e1/cgm", 
    "rssi": 194, 
    "type": "sgv", 
    "glucose": 107
  }, 
  {
    "trend_arrow": "FLAT", 
    "system_time": "2017-01-07T13:59:36", 
    "noise": 1, 
    "direction": "Flat", 
    "sgv": 108, 
    "display_time": "2017-01-07T06:13:35", 
    "date": 1483798415000.0, 
    "dateString": "2017-01-07T06:13:35", 
    "unfiltered": 112272, 
    "filtered": 108688, 
    "device": "openaps://indy-e1/cgm", 
    "rssi": 195, 
    "type": "sgv", 
    "glucose": 108
  }, 
  {
    "trend_arrow": "FLAT", 
    "system_time": "2017-01-07T13:54:37", 
    "noise": 1, 
    "direction": "Flat", 
    "sgv": 106, 
    "display_time": "2017-01-07T06:08:35", 
    "date": 1483798115000.0, 
    "dateString": "2017-01-07T06:08:35", 
    "unfiltered": 110576, 
    "filtered": 106560, 
    "device": "openaps://indy-e1/cgm", 
    "rssi": 448, 
    "type": "sgv", 
    "glucose": 106
  }, 
  {
    "trend_arrow": "FLAT", 
    "system_time": "2017-01-07T13:49:36", 
    "noise": 1, 
    "direction": "Flat", 
    "sgv": 105, 
    "display_time": "2017-01-07T06:03:35", 
    "date": 1483797815000.0, 
    "dateString": "2017-01-07T06:03:35", 
    "unfiltered": 109424, 
    "filtered": 106112, 
    "device": "openaps://indy-e1/cgm", 
    "rssi": 201, 
    "type": "sgv", 
    "glucose": 105
  }, 
  {
    "trend_arrow": "FLAT", 
    "system_time": "2017-01-07T13:44:36", 
    "noise": 1, 
    "direction": "Flat", 
    "sgv": 101, 
    "display_time": "2017-01-07T05:58:35", 
    "date": 1483797515000.0, 
    "dateString": "2017-01-07T05:58:35", 
    "unfiltered": 106240, 
    "filtered": 106912, 
    "device": "openaps://indy-e1/cgm", 
    "rssi": 201, 
    "type": "sgv", 
    "glucose": 101
  }
]