[
  {
    "trend_arrow": "45_DOWN", 
    "display_time": "2016-12-22T11:24:11-08:00", 
    "noise": 1, 
    "system_time": "2016-12-22T19:10:41-08:00", 
    "direction": "FortyFiveDown", 
    "sgv": 105, 
    "dateString": "2016-12-22T11:24:11-08:00", 
    "device": "openaps://indy-e1/cgm", 
    "unfiltered": 123808, 
    "rssi": 196, 
    "date": 1482434651000, 
    "filtered": 130832, 
    "type": "sgv", 
    "glucose": 105
  }, 
  {
    "trend_arrow": "FLAT", 
    "display_time": "2016-12-22T11:19:11-08:00", 
    "noise": 1, 
    "system_time": "2016-12-22T19:05:41-08:00", 
    "direction": "Flat", 
    "sgv": 111, 
    "dateString": "2016-12-22T11:19:11-08:00", 
    "device": "openaps://indy-e1/cgm", 
    "unfiltered": 128368, 
    "rssi": 194, 
    "date": 1482434351000, 
    "filtered": 134208, 
    "type": "sgv", 
    "glucose": 111
  }
]