[
  {
    "trend_arrow": "FLAT", 
    "display_time": "2016-12-16T07:04:25-08:00", 
    "noise": 1, 
    "system_time": "2016-12-16T13:56:49-08:00", 
    "direction": "Flat", 
    "sgv": 107, 
    "dateString": "2016-12-16T07:04:25-08:00", 
    "device": "openaps://indy-e1/cgm", 
    "unfiltered": 128560, 
    "rssi": 196, 
    "date": 1481900665000, 
    "filtered": 124032, 
    "type": "sgv", 
    "glucose": 107
  }, 
  {
    "trend_arrow": "FLAT", 
    "display_time": "2016-12-16T06:59:25-08:00", 
    "noise": 1, 
    "system_time": "2016-12-16T13:51:48-08:00", 
    "direction": "Flat", 
    "sgv": 104, 
    "dateString": "2016-12-16T06:59:25-08:00", 
    "device": "openaps://indy-e1/cgm", 
    "unfiltered": 125152, 
    "rssi": 190, 
    "date": 1481900365000, 
    "filtered": 121664, 
    "type": "sgv", 
    "glucose": 104
  }
]