[
  {
    "trend_arrow": "FLAT", 
    "display_time": "2016-12-28T18:25:00-08:00", 
    "noise": 1, 
    "system_time": "2016-12-29T02:11:21-08:00", 
    "direction": "Flat", 
    "sgv": 206, 
    "dateString": "2016-12-28T18:25:00-08:00", 
    "device": "openaps://indy-e1/cgm", 
    "unfiltered": 203040, 
    "rssi": 192, 
    "date": 1482978300000, 
    "filtered": 199040, 
    "type": "sgv", 
    "glucose": 206
  }, 
  {
    "trend_arrow": "45_UP", 
    "display_time": "2016-12-28T18:20:00-08:00", 
    "noise": 1, 
    "system_time": "2016-12-29T02:06:21-08:00", 
    "direction": "FortyFiveUp", 
    "sgv": 205, 
    "dateString": "2016-12-28T18:20:00-08:00", 
    "device": "openaps://indy-e1/cgm", 
    "unfiltered": 202048, 
    "rssi": 188, 
    "date": 1482978000000, 
    "filtered": 194688, 
    "type": "sgv", 
    "glucose": 205
  }
]