[
  {
    "trend_arrow": "NOT_COMPUTABLE", 
    "system_time": "2016-12-25T23:36:34", 
    "noise": 1, 
    "direction": "NOT COMPUTABLE", 
    "sgv": 205, 
    "display_time": "2016-12-25T15:50:14", 
    "date": 1482709814000.0, 
    "dateString": "2016-12-25T15:50:14", 
    "unfiltered": 212288, 
    "filtered": 211584, 
    "device": "openaps://indy-e1/cgm", 
    "rssi": 426, 
    "type": "sgv", 
    "glucose": 205
  }, 
  {
    "trend_arrow": "45_UP", 
    "system_time": "2016-12-25T23:11:35", 
    "noise": 1, 
    "direction": "FortyFiveUp", 
    "sgv": 195, 
    "display_time": "2016-12-25T15:25:14", 
    "date": 1482708314000.0, 
    "dateString": "2016-12-25T15:25:14", 
    "unfiltered": 202688, 
    "filtered": 190208, 
    "device": "openaps://indy-e1/cgm", 
    "rssi": 683, 
    "type": "sgv", 
    "glucose": 195
  }
]