[
  {
    "trend_arrow": "45_DOWN", 
    "display_time": "2017-01-04T13:34:48-08:00", 
    "noise": 1, 
    "system_time": "2017-01-04T21:34:08-08:00", 
    "direction": "FortyFiveDown", 
    "sgv": 80, 
    "dateString": "2017-01-04T13:34:48-08:00", 
    "device": "openaps://indy-e1/cgm", 
    "unfiltered": 93376, 
    "rssi": 177, 
    "date": 1483565688000, 
    "filtered": 106592, 
    "type": "sgv", 
    "glucose": 80
  }, 
  {
    "trend_arrow": "45_DOWN", 
    "display_time": "2017-01-04T13:29:48-08:00", 
    "noise": 1, 
    "system_time": "2017-01-04T21:29:08-08:00", 
    "direction": "FortyFiveDown", 
    "sgv": 88, 
    "dateString": "2017-01-04T13:29:48-08:00", 
    "device": "openaps://indy-e1/cgm", 
    "unfiltered": 100176, 
    "rssi": 187, 
    "date": 1483565388000, 
    "filtered": 112064, 
    "type": "sgv", 
    "glucose": 88
  }
]